spectral_density/KPM.py
spectral_density/SLQ.py
spectral_density/__init__.py
spectral_density/lanczos.py
spectral_density/reference_density.py
spectral_density-0.1.0.dist-info/WHEEL
spectral_density-0.1.0.dist-info/METADATA
spectral_density-0.1.0.dist-info/RECORD
