Metadata-Version: 2.1
Name: spectral_density
Version: 0.1.0
Summary: Spectrum adaptive spectral densities
Author-email: Tyler Chen <tyler.chen@nyu.edu>
Requires-Python: >=3.8
Classifier: Development Status :: 3 - Alpha
Classifier: License :: OSI Approved :: MIT License
Classifier: Natural Language :: English
Classifier: Operating System :: OS Independent
Classifier: Programming Language :: Python
Classifier: Programming Language :: Python :: 3.8
Classifier: Programming Language :: Python :: 3.9
Requires-Dist: numpy>=1.17
Requires-Dist: scipy>=1.4
Project-URL: Bug Tracker, https://github.com/tchen-reserach/spectral_density/issues
Project-URL: Homepage, https://github.com/tchen-research/spectral_density
